testando_pypi_www/__init__.py
testando_pypi_www/main.py
testando_pypi_www-0.0.2.dist-info/METADATA
testando_pypi_www-0.0.2.dist-info/WHEEL
testando_pypi_www-0.0.2.dist-info/licenses/LICENSE
testando_pypi_www-0.0.2.dist-info/RECORD
