Metadata-Version: 2.4
Name: testando_pypi_www
Version: 0.0.2
Summary: A test package for PyPI publishing
Project-URL: Homepage, https://github.com/rafaelpadilla/test-pypi-www
Project-URL: Repository, https://github.com/rafaelpadilla/test-pypi-www
Project-URL: Issues, https://github.com/rafaelpadilla/test-pypi-www/issues
Author-email: Rafael Padilla <eng.rafaelpadilla@gmail.com>
License: MIT
License-File: LICENSE
Keywords: 3Wtoolkit,example,pypi
Classifier: Development Status :: 3 - Alpha
Classifier: Intended Audience :: Developers
Classifier: License :: OSI Approved :: MIT License
Classifier: Programming Language :: Python :: 3
Classifier: Programming Language :: Python :: 3.8
Classifier: Programming Language :: Python :: 3.9
Classifier: Programming Language :: Python :: 3.10
Classifier: Programming Language :: Python :: 3.11
Classifier: Programming Language :: Python :: 3.12
Classifier: Programming Language :: Python :: 3.13
Requires-Python: >=3.13
Requires-Dist: numpy>=2.3.0
